[
    {
      "nftId": 10099712,
      "playerName": "Luka Doncic",
      "cost": 10
    },
    {
      "nftId": 12056743,
      "playerName": "Ja Morant",
      "cost": 10
    },
    {
      "nftId": 4870675,
      "playerName": "Bradley Beal",
      "cost": 10
    },
    {
      "nftId": 34561573,
      "playerName": "Immanuel Quickley",
      "cost": 10
    },
    {
      "nftId": 6900442,
      "playerName": "Brook Lopez",
      "cost": 10
    },
    {
      "nftId": 5748804,
      "playerName": "James Wiseman",
      "cost": 10
    },
    {
      "nftId": 3436840,
      "playerName": "RJ Barrett",
      "cost": 10
    },
    {
      "nftId": 1086415,
      "playerName": "Markelle Fultz",
      "cost": 10
    },
    {
      "nftId": 7138246,
      "playerName": "Ben Simmons",
      "cost": 10
    },
    {
      "nftId": 1470395,
      "playerName": "Pascal Siakam",
      "cost": 10
    },
    {
      "nftId": 5193792,
      "playerName": "Theo Maledon",
      "cost": 10
    },
    {
      "nftId": 1303379,
      "playerName": "Marcus Smart",
      "cost": 10
    },
    {
      "nftId": 8964304,
      "playerName": "Cameron Payne",
      "cost": 10
    }
  ]